pycapnp_wheels-0.6.4.dist-info/entry_points.txt
pycapnp_wheels-0.6.4.dist-info/METADATA
pycapnp_wheels-0.6.4.dist-info/RECORD
pycapnp_wheels-0.6.4.dist-info/top_level.txt
pycapnp_wheels-0.6.4.dist-info/WHEEL
pycapnp_wheels-0.6.4.dist-info/LICENSE
capnp/version.py
capnp/_gen.py
capnp/__init__.py
capnp/schema.capnp
capnp/__init__.pxd
capnp/c++.capnp
capnp/helpers/helpers.pxd
capnp/helpers/rpcHelper.h
capnp/helpers/capabilityHelper.h
capnp/helpers/asyncHelper.h
capnp/helpers/checkCompiler.h
capnp/helpers/non_circular.pxd
capnp/helpers/serialize.h
capnp/helpers/fixMaybe.h
capnp/helpers/__init__.pxd
capnp/includes/schema_cpp.pxd
capnp/includes/types.pxd
capnp/includes/capnp_cpp.pxd
capnp/includes/__init__.pxd
capnp/templates/module.pyx
capnp/templates/setup.py.tmpl
capnp/lib/pickle_helper.py
capnp/lib/capnp.pyx
capnp/lib/capnp.cpython-36m-aarch64-linux-gnu.so
capnp/lib/__init__.py
capnp/lib/__init__.pxd
capnp/lib/capnp.pxd
