Metadata-Version: 2.1
Name: pycapnp-wheels
Version: 0.6.4
Summary: A cython wrapping of the C++ Cap'n Proto library
Home-page: https://github.com/jparyani/pycapnp
Author: Jason Paryani
Author-email: pypi-contact@jparyani.com
License: BSD
Download-URL: https://github.com/jparyani/pycapnp/archive/v0.6.4.zip
Keywords: capnp,capnproto,Cap'n Proto
Platform: UNKNOWN
Classifier: Development Status :: 4 - Beta
Classifier: Intended Audience :: Developers
Classifier: License :: OSI Approved :: BSD License
Classifier: Operating System :: MacOS :: MacOS X
Classifier: Operating System :: POSIX
Classifier: Programming Language :: C++
Classifier: Programming Language :: Cython
Classifier: Programming Language :: Python :: 2
Classifier: Programming Language :: Python :: 2.7
Classifier: Programming Language :: Python :: 3
Classifier: Programming Language :: Python :: 3.4
Classifier: Programming Language :: Python :: 3.5
Classifier: Programming Language :: Python :: 3.6
Classifier: Programming Language :: Python :: Implementation :: PyPy
Classifier: Topic :: Communications
License-File: LICENSE
